fermat/Fermat.py
fermat/__init__.py
fermat/clusterize.py
fermat/kmedoids.py
fermat/path_methods/__init__.py
fermat/path_methods/dijkstra_method.py
fermat/path_methods/distance_calculator_method.py
fermat/path_methods/floyd_warshall_method.py
fermat/path_methods/landmarks_method.py
fermat-0.2.7.dist-info/LICENSE
fermat-0.2.7.dist-info/METADATA
fermat-0.2.7.dist-info/WHEEL
fermat-0.2.7.dist-info/top_level.txt
fermat-0.2.7.dist-info/RECORD
