Metadata-Version: 2.1
Name: fermat
Version: 0.2.7
Summary: library to compute fermat distance
Home-page: https://bitbucket.org/aristas/fermat
Author: Facundo Sapienza
Author-email: support@aristas.com.ar
License: MIT
Platform: UNKNOWN
Classifier: License :: OSI Approved :: MIT License
Classifier: Operating System :: OS Independent
Requires-Python: >=3.8
Requires-Dist: scipy
Requires-Dist: numpy
Requires-Dist: scikit-learn
